apologist/__init__.py
apologist/_base_client.py
apologist/_client.py
apologist/_compat.py
apologist/_constants.py
apologist/_exceptions.py
apologist/_files.py
apologist/_models.py
apologist/_qs.py
apologist/_resource.py
apologist/_response.py
apologist/_streaming.py
apologist/_types.py
apologist/_version.py
apologist/py.typed
apologist/_utils/__init__.py
apologist/_utils/_compat.py
apologist/_utils/_datetime_parse.py
apologist/_utils/_logs.py
apologist/_utils/_proxy.py
apologist/_utils/_reflection.py
apologist/_utils/_resources_proxy.py
apologist/_utils/_streams.py
apologist/_utils/_sync.py
apologist/_utils/_transform.py
apologist/_utils/_typing.py
apologist/_utils/_utils.py
apologist/lib/.keep
apologist/resources/__init__.py
apologist/resources/pet.py
apologist/resources/user.py
apologist/resources/store/__init__.py
apologist/resources/store/order.py
apologist/resources/store/store.py
apologist/types/__init__.py
apologist/types/pet.py
apologist/types/pet_create_params.py
apologist/types/pet_find_by_status_params.py
apologist/types/pet_find_by_status_response.py
apologist/types/pet_find_by_tags_params.py
apologist/types/pet_find_by_tags_response.py
apologist/types/pet_update_params.py
apologist/types/pet_update_with_form_params.py
apologist/types/pet_upload_image_params.py
apologist/types/pet_upload_image_response.py
apologist/types/store_list_inventory_response.py
apologist/types/user.py
apologist/types/user_create_params.py
apologist/types/user_create_with_list_params.py
apologist/types/user_login_params.py
apologist/types/user_login_response.py
apologist/types/user_param.py
apologist/types/user_update_params.py
apologist/types/store/__init__.py
apologist/types/store/order.py
apologist/types/store/order_create_params.py
apologist-1.0.1.dist-info/METADATA
apologist-1.0.1.dist-info/WHEEL
apologist-1.0.1.dist-info/licenses/LICENSE
apologist-1.0.1.dist-info/RECORD
